roc/__init__.py
roc/rap/__init__.py
roc/rap/commands.py
roc/rap/config/__init__.py
roc/rap/constants.py
roc/rap/descriptor.json
roc/rap/exceptions.py
roc/rap/tasks/__init__.py
roc/rap/tasks/bia/__init__.py
roc/rap/tasks/bia/bias.py
roc/rap/tasks/bia/current.py
roc/rap/tasks/bia/sweep.py
roc/rap/tasks/lfr/__init__.py
roc/rap/tasks/lfr/bp/TM_LFR_BP1.h
roc/rap/tasks/lfr/bp/TM_LFR_BP2.h
roc/rap/tasks/lfr/bp/__init__.py
roc/rap/tasks/lfr/bp/convert_BP.py
roc/rap/tasks/lfr/normal_burst.py
roc/rap/tasks/lfr/sbm1.py
roc/rap/tasks/lfr/sbm2.py
roc/rap/tasks/lfr/utils.pyx
roc/rap/tasks/tds/__init__.py
roc/rap/tasks/tds/lfm_cwf.pyx
roc/rap/tasks/tds/lfm_psd.pyx
roc/rap/tasks/tds/lfm_rswf.pyx
roc/rap/tasks/tds/lfm_sm.pyx
roc/rap/tasks/tds/normal_hist1d.py
roc/rap/tasks/tds/normal_hist2d.pyx
roc/rap/tasks/tds/normal_mamp.pyx
roc/rap/tasks/tds/normal_rswf.pyx
roc/rap/tasks/tds/normal_stat.py
roc/rap/tasks/tds/normal_tswf.pyx
roc/rap/tasks/tds/sbm.py
roc/rap/tasks/tds/utils.pyx
roc/rap/tasks/thr/__init__.py
roc/rap/tasks/thr/calibration_hfr.pyx
roc/rap/tasks/thr/calibration_tnr.pyx
roc/rap/tasks/thr/hfr.pyx
roc/rap/tasks/thr/hfr_list.py
roc/rap/tasks/thr/hfr_time_log.py
roc/rap/tasks/thr/normal_burst_hfr.pyx
roc/rap/tasks/thr/normal_burst_tnr.pyx
roc/rap/tasks/thr/science_spectral_power.pyx
roc/rap/tasks/thr/science_tools.pyx
roc/rap/tasks/thr/thr.py
roc/rap/tasks/thr/tnr.pyx
roc/rap/tasks/utils.py
roc/rap/tests/__init__.py
roc/rap/tests/test_tasks_bia.py
roc/rap/tests/test_tasks_lfr.py
roc/rap/tests/test_tasks_tds.py
roc/rap/tests/test_tasks_thr.py
roc/rap/tests/tests.py
roc/rap/tools/__init__.py
roc/rap/tools/tools.py
roc/rap/tasks/lfr/utils.c
roc/rap/tasks/lfr/utils.cpython-312-x86_64-linux-gnu.so
roc/rap/tasks/tds/lfm_cwf.c
roc/rap/tasks/tds/lfm_cwf.cpython-312-x86_64-linux-gnu.so
roc/rap/tasks/tds/lfm_psd.c
roc/rap/tasks/tds/lfm_psd.cpython-312-x86_64-linux-gnu.so
roc/rap/tasks/tds/lfm_rswf.c
roc/rap/tasks/tds/lfm_rswf.cpython-312-x86_64-linux-gnu.so
roc_rap-1.6.0.dist-info/LICENSE
roc_rap-1.6.0.dist-info/METADATA
roc_rap-1.6.0.dist-info/WHEEL
roc_rap-1.6.0.dist-info/RECORD
